COPYRIGHT.txt
LICENSE.txt
setup.py
pushpage/CHANGES.txt
pushpage/README.txt
pushpage/__init__.py
pushpage/browser.py
pushpage/events.py
pushpage/interfaces.py
pushpage/meta.zcml
pushpage/version.txt
pushpage/z2.py
pushpage/zcml.py
pushpage.egg-info/PKG-INFO
pushpage.egg-info/not-zip-safe
pushpage.egg-info/requires.txt
pushpage.egg-info/top_level.txt
pushpage/tests/__init__.py
pushpage/tests/test_README.py
