Metadata-Version: 1.0
Name: pushpage
Version: 0.3
Summary: Push-mode ZPT pages
Home-page: http://agendaless.com/Members/tseaver/software/pushpage
Author: Tres Seaver, Agendaless Consulting
Author-email: tseaver@agendaless.com
License: ZPL 2.1
Platform: UNKNOWN
